src/__init__.py
src/__main__.py
src/_version.py
rockford-0.0.1.dist-info/METADATA
rockford-0.0.1.dist-info/WHEEL
rockford-0.0.1.dist-info/entry_points.txt
rockford-0.0.1.dist-info/top_level.txt
rockford-0.0.1.dist-info/RECORD
